comet_ice_sublimation/__init__.py
comet_ice_sublimation/comet_ice_sublimation.py
comet_ice_sublimation/energy_balance/__init__.py
comet_ice_sublimation/energy_balance/energy_balance.py
comet_ice_sublimation/heat_of_sublimation/__init__.py
comet_ice_sublimation/heat_of_sublimation/heat_of_sublimation.py
comet_ice_sublimation/heat_of_sublimation/heat_of_sublimation_carbon_dioxide.py
comet_ice_sublimation/heat_of_sublimation/heat_of_sublimation_carbon_monoxide.py
comet_ice_sublimation/heat_of_sublimation/heat_of_sublimation_result.py
comet_ice_sublimation/heat_of_sublimation/heat_of_sublimation_water.py
comet_ice_sublimation/heat_of_sublimation/heat_of_sublimation_water_methane.py
comet_ice_sublimation/model_input/__init__.py
comet_ice_sublimation/model_input/sublimation_model_input.py
comet_ice_sublimation/model_output/__init__.py
comet_ice_sublimation/model_output/sublimation_model_output.py
comet_ice_sublimation/model_runner/__init__.py
comet_ice_sublimation/model_runner/model_runner.py
comet_ice_sublimation/model_saver/__init__.py
comet_ice_sublimation/model_saver/model_saver.py
comet_ice_sublimation/molecular_species/__init__.py
comet_ice_sublimation/molecular_species/molecular_species.py
comet_ice_sublimation/molecular_species/starting_temperatures.py
comet_ice_sublimation/parse_arguments.py
comet_ice_sublimation/physical_constants/__init__.py
comet_ice_sublimation/physical_constants/physical_constants.py
comet_ice_sublimation/surface_geometry/__init__.py
comet_ice_sublimation/surface_geometry/surface_geometry.py
comet_ice_sublimation-1.0.0.dist-info/LICENSE
comet_ice_sublimation-1.0.0.dist-info/METADATA
comet_ice_sublimation-1.0.0.dist-info/WHEEL
comet_ice_sublimation-1.0.0.dist-info/entry_points.txt
comet_ice_sublimation-1.0.0.dist-info/RECORD
