Metadata-Version: 2.1
Name: comet_ice_sublimation
Version: 1.0.0
Summary: Rapid rotator model of ice sublimation for comet nuclei
License: LICENSE
Author: Shawn Oset
Requires-Python: >=3.11,<3.13
Classifier: License :: Other/Proprietary License
Classifier: Programming Language :: Python :: 3
Classifier: Programming Language :: Python :: 3.11
Classifier: Programming Language :: Python :: 3.12
Requires-Dist: numpy (>=2.2.2,<3.0.0)
